{
    "mdb_source_id": 943,
    "data_type": "gtfs",
    "provider": "Citylink",
    "location": {
        "country_code": "IE",
        "bounding_box": {
            "minimum_latitude": 51.8489757069344,
            "maximum_latitude": 53.5564907728219,
            "minimum_longitude": -10.1119327202063,
            "maximum_longitude": -6.24168630800514,
            "extracted_on": "2022-03-17T18:51:01+00:00"
        }
    },
    "urls": {
        "direct_download": "https://www.transportforireland.ie/transitData/google_transit_citylink.zip",
        "latest": "https://storage.googleapis.com/storage/v1/b/mdb-latest/o/ie-unknown-citylink-gtfs-943.zip?alt=media",
        "license": "https://data.gov.ie/licence"
    }
}