{
    "mdb_source_id": 2114,
    "data_type": "gtfs",
    "provider": "Transport Urban Sinaia",
    "status": "active",
    "location": {
        "country_code": "RO",
        "subdivision_name": "Prahova",
        "municipality": "Sinaia",
        "bounding_box": {
            "minimum_latitude": 45.312519,
            "maximum_latitude": 45.368809,
            "minimum_longitude": 25.47452,
            "maximum_longitude": 25.568499,
            "extracted_on": "2024-10-12T10:45:12+00:00"
        }
    },
    "urls": {
        "direct_download": "https://external.gtfs.ro/sinaia/SINAIA.zip",
        "latest": "https://storage.googleapis.com/storage/v1/b/mdb-latest/o/ro-prahova-transport-urban-sinaia-gtfs-2114.zip?alt=media"
    },
    "redirect": []
}