{
    "mdb_source_id": 1213,
    "data_type": "gtfs",
    "provider": "Epic Mountain Express",
    "feed_contact_email": "support+test+cme-co-us@trilliumtransit.com",
    "location": {
        "country_code": "US",
        "subdivision_name": "Colorado",
        "bounding_box": {
            "minimum_latitude": 39.18745,
            "maximum_latitude": 39.848793529552,
            "minimum_longitude": -107.32773,
            "maximum_longitude": -104.67285727756,
            "extracted_on": "2022-04-25T23:24:39+00:00"
        }
    },
    "urls": {
        "direct_download": "https://data.trilliumtransit.com/gtfs/cme-co-us/cme-co-us.zip",
        "authentication_type": 0,
        "latest": "https://storage.googleapis.com/storage/v1/b/mdb-latest/o/us-colorado-epic-mountain-express-gtfs-1213.zip?alt=media",
        "license": "https://colorado-gtfs.trilliumtransit.com/"
    },
    "redirect": []
}