{
    "mdb_source_id": 379,
    "data_type": "gtfs",
    "provider": "Pulaski Area Transit (PAT)",
    "status": "deprecated",
    "location": {
        "country_code": "US",
        "subdivision_name": "Virginia",
        "municipality": "Pulaski",
        "bounding_box": {
            "minimum_latitude": 37.0389235602136,
            "maximum_latitude": 37.0682116663451,
            "minimum_longitude": -80.7822820685722,
            "maximum_longitude": -80.7493873998037,
            "extracted_on": "2022-03-16T15:27:12+00:00"
        }
    },
    "urls": {
        "direct_download": "https://ridesolutions.org/gtfs/pulaski-va-us.zip",
        "authentication_type": 0,
        "latest": "https://storage.googleapis.com/storage/v1/b/mdb-latest/o/us-virginia-pulaski-area-transit-pat-gtfs-379.zip?alt=media"
    },
    "redirect": [
        {
            "id": "2198",
            "comment": " "
        }
    ]
}